progscheduler/__init__.py
progscheduler/app.py
progscheduler/jobs.py
progscheduler/scheduler.py
progscheduler/settings/__init__.py
progscheduler/settings/commands.py
progscheduler/settings/generic_arguments.py
progscheduler/settings/manager.py
progscheduler/settings/specific_arguments.py
progscheduler/utils/__init__.py
progscheduler/utils/date.py
progscheduler/utils/directory.py
progscheduler/utils/log.py
progscheduler/utils/reflection.py
progscheduler/utils/yaml.py
progscheduler/version/__init__.py
progscheduler/version/progsettings.py
progscheduler/version/progsettings.yaml
progscheduler-2.3.5.dist-info/LICENSE
progscheduler-2.3.5.dist-info/METADATA
progscheduler-2.3.5.dist-info/WHEEL
progscheduler-2.3.5.dist-info/entry_points.txt
progscheduler-2.3.5.dist-info/top_level.txt
progscheduler-2.3.5.dist-info/RECORD
