Metadata-Version: 2.1
Name: progscheduler
Version: 2.3.5
Summary: A simple automated task to schedule files to open in specific days of the week or every day at startup or at specific time of the day.
Home-page: https://github.com/zaytiri/program-scheduler
Author: zaytiri
Project-URL: GitHub, https://github.com/zaytiri/program-scheduler
Project-URL: Changelog, https://github.com/zaytiri/program-scheduler/blob/main/CHANGELOG.md
Keywords: program,schedule,scheduler,startup,days,open,files,folders
Classifier: Environment :: Console
Classifier: Intended Audience :: Developers
Classifier: License :: OSI Approved :: MIT License
Classifier: Operating System :: OS Independent
Classifier: Programming Language :: Python :: 3
Requires-Python: >=3.10.6
License-File: LICENSE
Requires-Dist: PyYAML ~=6.0
Requires-Dist: schedule ~=1.1.0
